cardano_mass_payments/__init__.py
cardano_mass_payments/cache.py
cardano_mass_payments/classes.py
cardano_mass_payments/settings.py
cardano_mass_payments/commands/__init__.py
cardano_mass_payments/commands/mass_payments.py
cardano_mass_payments/constants/__init__.py
cardano_mass_payments/constants/commands.py
cardano_mass_payments/constants/common.py
cardano_mass_payments/constants/exceptions.py
cardano_mass_payments/utils/__init__.py
cardano_mass_payments/utils/cli_utils.py
cardano_mass_payments/utils/common.py
cardano_mass_payments/utils/pycardano_utils.py
cardano_mass_payments/utils/script_utils.py
tests/__init__.py
tests/mock_responses.py
tests/mock_utils.py
tests/test_cli_function_tests/__init__.py
tests/test_cli_function_tests/test_create_transaction_command.py
tests/test_cli_function_tests/test_create_transaction_file.py
tests/test_cli_function_tests/test_get_latest_slot_number.py
tests/test_cli_function_tests/test_get_protocol_parameters.py
tests/test_cli_function_tests/test_get_stake_address_balance.py
tests/test_cli_function_tests/test_get_staking_address.py
tests/test_cli_function_tests/test_get_total_amount_plus_fee.py
tests/test_cli_function_tests/test_get_transaction_byte_size.py
tests/test_cli_function_tests/test_get_transaction_fee.py
tests/test_cli_function_tests/test_get_utxo_hash.py
tests/test_cli_function_tests/test_get_wallet_utxo.py
tests/test_cli_function_tests/test_sign_tx_file.py
tests/test_process/__init__.py
tests/test_process/test_script_process.py
tests/test_script_function_tests/__init__.py
tests/test_script_function_tests/test_adjust_utxos.py
tests/test_script_function_tests/test_dust_collect.py
tests/test_script_function_tests/test_generate_bash_script.py
tests/test_script_function_tests/test_group_output_utxo.py
tests/test_script_function_tests/test_parse_payment_utxo_file.py
tests/test_script_function_tests/test_parse_sources_csv_file.py
tests/test_script_function_tests/test_preparation_step.py
cardano_mass_payments-0.1.5.dist-info/LICENSE
cardano_mass_payments-0.1.5.dist-info/METADATA
cardano_mass_payments-0.1.5.dist-info/WHEEL
cardano_mass_payments-0.1.5.dist-info/entry_points.txt
cardano_mass_payments-0.1.5.dist-info/top_level.txt
cardano_mass_payments-0.1.5.dist-info/RECORD
