Metadata-Version: 2.1
Name: cardano-mass-payments
Version: 0.1.5
Summary: A tool for handling mass payments for Cardano (ADA)
Home-page: https://github.com/adaplus/cardano-mass-payments
Author: ADAPlus
Author-email: hello@adaplus.io
Classifier: Development Status :: 3 - Alpha
Classifier: Intended Audience :: Developers
Classifier: Natural Language :: English
Classifier: License :: OSI Approved :: GNU General Public License v3 (GPLv3)
Classifier: Topic :: Office/Business :: Financial :: Accounting
Classifier: Programming Language :: Python :: 3.7
Classifier: Programming Language :: Python :: 3.8
Classifier: Programming Language :: Python :: 3.9
Classifier: Programming Language :: Python :: 3.10
Requires-Python: >=3.7
License-File: LICENSE
Requires-Dist: pycardano (==0.7.0)
